rmw_test_fixture_implementation/_dummy.cpython-310-x86_64-linux-gnu.so
ros_rmw_test_fixture_implementation-0.14.5.data/data/lib/librmw_test_fixture_implementation.so
ros_rmw_test_fixture_implementation-0.14.5.data/data/lib/python3.10/site-packages/rmw_test_fixture_implementation/__init__.py
ros_rmw_test_fixture_implementation-0.14.5.data/data/lib/python3.10/site-packages/rmw_test_fixture_implementation/_rmw_test_fixture_implementation.so
ros_rmw_test_fixture_implementation-0.14.5.data/data/lib/python3.10/site-packages/rmw_test_fixture_implementation/__pycache__/__init__.cpython-310.pyc
ros_rmw_test_fixture_implementation-0.14.5.data/data/lib/python3.10/site-packages/rmw_test_fixture_implementation-0.14.4-py3.10.egg-info/PKG-INFO
ros_rmw_test_fixture_implementation-0.14.5.data/data/lib/python3.10/site-packages/rmw_test_fixture_implementation-0.14.4-py3.10.egg-info/SOURCES.txt
ros_rmw_test_fixture_implementation-0.14.5.data/data/lib/python3.10/site-packages/rmw_test_fixture_implementation-0.14.4-py3.10.egg-info/dependency_links.txt
ros_rmw_test_fixture_implementation-0.14.5.data/data/lib/python3.10/site-packages/rmw_test_fixture_implementation-0.14.4-py3.10.egg-info/top_level.txt
ros_rmw_test_fixture_implementation-0.14.5.data/data/lib/rmw_test_fixture_implementation/run_rmw_isolated
ros_rmw_test_fixture_implementation-0.14.5.data/data/share/ament_index/resource_index/package_run_dependencies/rmw_test_fixture_implementation
ros_rmw_test_fixture_implementation-0.14.5.data/data/share/ament_index/resource_index/packages/rmw_test_fixture_implementation
ros_rmw_test_fixture_implementation-0.14.5.data/data/share/ament_index/resource_index/parent_prefix_path/rmw_test_fixture_implementation
ros_rmw_test_fixture_implementation-0.14.5.data/data/share/rmw_test_fixture_implementation/local_setup.bash
ros_rmw_test_fixture_implementation-0.14.5.data/data/share/rmw_test_fixture_implementation/local_setup.dsv
ros_rmw_test_fixture_implementation-0.14.5.data/data/share/rmw_test_fixture_implementation/local_setup.sh
ros_rmw_test_fixture_implementation-0.14.5.data/data/share/rmw_test_fixture_implementation/local_setup.zsh
ros_rmw_test_fixture_implementation-0.14.5.data/data/share/rmw_test_fixture_implementation/package.dsv
ros_rmw_test_fixture_implementation-0.14.5.data/data/share/rmw_test_fixture_implementation/package.xml
ros_rmw_test_fixture_implementation-0.14.5.data/data/share/rmw_test_fixture_implementation/cmake/ament_cmake_export_dependencies-extras.cmake
ros_rmw_test_fixture_implementation-0.14.5.dist-info/METADATA
ros_rmw_test_fixture_implementation-0.14.5.dist-info/WHEEL
ros_rmw_test_fixture_implementation-0.14.5.dist-info/top_level.txt
ros_rmw_test_fixture_implementation-0.14.5.dist-info/RECORD
