Metadata-Version: 2.4
Name: ros-rmw-test-fixture-implementation
Version: 0.14.5
Summary: Wheel for the rmw_test_fixture_implementation (ros-rmw-test-fixture-implementation) ROS 2 package.
Requires-Dist: ros-rmw-test-fixture~=0.14.5
Requires-Dist: ros-rpyutils~=0.6.3
Requires-Dist: ros-rmw~=7.8.2
Requires-Dist: ros-rcpputils~=2.13.5
Requires-Dist: ros-rcutils~=6.9.8
Dynamic: description
Dynamic: description-content-type
Dynamic: requires-dist
Dynamic: summary
